[
    {
        "event_name": "ONCE UPON Ａ TIME 飾品快閃店",
        "event_image": "https://media.huashan1914.com/WebUPD/huashan1914/exhibition/1920x1080-2_21050614503104860.jpg",
        "event_date": "2021.04.01 - 06.30",
        "event_type": "期間限定店",
        "event_link": "https://www.huashan1914.com//w/huashan1914/exhibition_21042009500201213"
    },
    {
        "event_name": "品嚐人蔘 林俞槿emma個展",
        "event_image": "https://media.huashan1914.com/WebUPD/huashan1914/exhibition/2_21051112542591960.jpg",
        "event_date": "2021.04.10 - 07.04",
        "event_type": "期間限定店\n品牌活動",
        "event_link": "https://www.huashan1914.com//w/huashan1914/exhibition_21051112345521165"
    },
    {
        "event_name": "外星萌主爭霸戰-台北對決擂台",
        "event_image": "https://media.huashan1914.com/WebUPD/huashan1914/exhibition/%e5%9c%961.%e6%9c%80%e5%bc%b7%e7%88%ad%e9%9c%b8%ef%bc%81%e5%8f%b2%e8%bf%aa%e5%a5%87%e3%80%81%e4%b8%89%e7%9c%bc%e6%80%aa%e3%80%8a%e5%a4%96%e6%98%9f%e8%90%8c%e4%b8%bb%e7%88%ad%e9%9c%b8%e6%88%b0-%e5%8f%b0%e5%8c%97%e5%b0%8d%e6%b1%ba%e6%93%82%e5%8f%b0%e3%80%8b5_14%e8%8f%af%e5%b1%b1%e7%99%bb%e5%a0%b4_21051119574075768.jpg",
        "event_date": "2021.05.14 - 07.04",
        "event_type": "期間限定店",
        "event_link": "https://www.huashan1914.com//w/huashan1914/exhibition_21051119574078676"
    },
    {
        "event_name": "P.Seven台灣茶香水-隱形衣特展",
        "event_image": "https://media.huashan1914.com/WebUPD/huashan1914/exhibition/%e6%93%b7%e5%8f%96_21032814370449643.JPG",
        "event_date": "2021.04.08 - 07.04",
        "event_type": "期間限定店",
        "event_link": "https://www.huashan1914.com//w/huashan1914/exhibition_21032814370450436"
    },
    {
        "event_name": "ASTROLOGY氣味星象漫遊",
        "event_image": "https://media.huashan1914.com/WebUPD/huashan1914/exhibition/210507_%e6%b0%a3%e5%91%b3%e6%bc%ab%e9%81%8a_%e4%b8%bb%e8%a6%96%e8%a6%ba_%e8%8f%af%e5%b1%b1%e7%a4%be%e7%be%a4-06_%e5%b0%ba%e5%af%b8B%20(1).jpg",
        "event_date": "2021.05.14 - 07.18",
        "event_type": "期間限定店\n品牌活動",
        "event_link": "https://www.huashan1914.com//w/huashan1914/exhibition_21051112241150676"
    },
    {
        "event_name": "暗通款曲 快閃餐吧 Underground River Pop-up Deli & Bar",
        "event_image": "https://media.huashan1914.com/WebUPD/huashan1914/exhibition/%e8%8f%af%e5%b1%b1_%e4%b8%bb%e9%a0%81%e6%9b%9d%e5%85%89.jpg",
        "event_date": "2021.05.18 - 07.30",
        "event_type": "展演活動\n品牌活動",
        "event_link": "https://www.huashan1914.com//w/huashan1914/exhibition_21052211510176911"
    },
    {
        "event_name": "【華山親子表藝節】找我劇場-心流工作坊",
        "event_image": "https://media.huashan1914.com/WebUPD/umaytheater/performance/436_21051314232540900.png",
        "event_date": "2021.06.20",
        "event_type": "【華山親子表藝節】工作坊\n表演藝術",
        "event_link": "https://www.huashan1914.com//w/umaytheater/performance_21040115375120617"
    },
    {
        "event_name": "跨界流行Rock ’n Roll",
        "event_image": "https://media.huashan1914.com/WebUPD/umaytheater/performance/B_1920x1080_21042212264150714.jpg",
        "event_date": "2021.06.27",
        "event_type": "表演\n表演藝術",
        "event_link": "https://www.huashan1914.com//w/umaytheater/performance_21042212052112802"
    },
    {
        "event_name": "【華山親子表藝節】夾腳拖劇團-小丑工作坊",
        "event_image": "https://media.huashan1914.com/WebUPD/umaytheater/performance/%e5%b0%8f%e4%b8%91%e5%b7%a5%e4%bd%9c%e5%9d%8a_21042310122401821.png",
        "event_date": "2021.07.03",
        "event_type": "【華山親子表藝節】工作坊\n表演藝術",
        "event_link": "https://www.huashan1914.com//w/umaytheater/performance_21040115403613065"
    },
    {
        "event_name": "【華山親子表藝節】夾腳拖劇團-扮裝工作坊",
        "event_image": "https://media.huashan1914.com/WebUPD/umaytheater/performance/uilfui_21042311331129227.png",
        "event_date": "2021.07.04",
        "event_type": "【華山親子表藝節】工作坊\n表演藝術",
        "event_link": "https://www.huashan1914.com//w/umaytheater/performance_21040115573070931"
    },
    {
        "event_name": "【華山親子表藝節】夾腳拖劇團-口技工作坊",
        "event_image": "https://media.huashan1914.com/WebUPD/umaytheater/performance/oipg.png",
        "event_date": "2021.07.11",
        "event_type": "【華山親子表藝節】工作坊\n表演藝術",
        "event_link": "https://www.huashan1914.com//w/umaytheater/performance_21040116242609987"
    },
    {
        "event_name": "華山親子表藝節×慢慢說工作坊「星球奇景」——色彩濾鏡",
        "event_image": "https://media.huashan1914.com/WebUPD/umaytheater/performance/%e5%96%ae%e5%bc%b5300dppi_%e8%89%b2%e5%bd%a9%e6%bf%be%e9%8f%a1_21050415110050214.jpg",
        "event_date": "2021.07.16",
        "event_type": "【華山親子表藝節】工作坊\n表演藝術",
        "event_link": "https://www.huashan1914.com//w/umaytheater/performance_21050415110053787"
    },
    {
        "event_name": "華山親子表藝節×慢慢說工作坊「星球迷宮」——探索號彈珠檯",
        "event_image": "https://media.huashan1914.com/WebUPD/umaytheater/performance/%e5%96%ae%e5%bc%b5300dppi_%e6%8e%a2%e7%b4%a2%e8%99%9f%e5%bd%88%e7%8f%a0%e6%aa%af_21050415481118945.jpg",
        "event_date": "2021.07.17",
        "event_type": "【華山親子表藝節】工作坊\n表演藝術",
        "event_link": "https://www.huashan1914.com//w/umaytheater/performance_21050415453747824"
    },
    {
        "event_name": "華山親子表藝節×慢慢說工作坊「星球主人翁」——印章自畫像",
        "event_image": "https://media.huashan1914.com/WebUPD/umaytheater/performance/%e5%96%ae%e5%bc%b5300dppi_%e5%8d%b0%e7%ab%a0%e8%87%aa%e7%95%ab%e5%83%8f_21050415510131525.jpg",
        "event_date": "2021.07.18",
        "event_type": "【華山親子表藝節】工作坊\n表演藝術",
        "event_link": "https://www.huashan1914.com//w/umaytheater/performance_21050415491391901"
    },
    {
        "event_name": "【華山親子表藝節】創造焦點-與馬戲同樂工作坊",
        "event_image": "https://media.huashan1914.com/WebUPD/umaytheater/performance/cykuy_21042311365346854.png",
        "event_date": "2021.07.10 - 07.18",
        "event_type": "【華山親子表藝節】工作坊\n表演藝術",
        "event_link": "https://www.huashan1914.com//w/umaytheater/performance_21040116140469403"
    },
    {
        "event_name": "【華山親子表藝節】磚木取夥故事劇場-「線在玩什麼？」——找到聲音裡的線條工作坊",
        "event_image": "https://media.huashan1914.com/WebUPD/umaytheater/performance/%e3%80%8c%e7%b7%9a%e5%9c%a8%e7%8e%a9%e4%bb%80%e9%ba%bc%ef%bc%9f%e3%80%8d%e2%80%94%e2%80%94%e6%89%be%e5%88%b0%e8%81%b2%e9%9f%b3%e8%a3%a1%e7%9a%84%e7%b7%9a%e6%a2%9d%e5%b7%a5%e4%bd%9c%e5%9d%8a_21042310233071837.png",
        "event_date": "2021.07.24",
        "event_type": "【華山親子表藝節】工作坊\n表演藝術",
        "event_link": "https://www.huashan1914.com//w/umaytheater/performance_21040116452209825"
    },
    {
        "event_name": "【華山親子表藝節】磚木取夥故事劇場-「在家爬山・在客廳冒險」——發揮空間想像力工作坊",
        "event_image": "https://media.huashan1914.com/WebUPD/umaytheater/performance/%e3%80%8c%e5%9c%a8%e5%ae%b6%e7%88%ac%e5%b1%b1%e3%83%bb%e5%9c%a8%e5%ae%a2%e5%bb%b3%e5%86%92%e9%9a%aa%e3%80%8d%e2%80%94%e2%80%94%e7%99%bc%e6%8f%ae%e7%a9%ba%e9%96%93%e6%83%b3%e5%83%8f%e5%8a%9b%e5%b7%a5%e4%bd%9c%e5%9d%8a_21042310250381835.png",
        "event_date": "2021.07.24",
        "event_type": "【華山親子表藝節】工作坊\n表演藝術",
        "event_link": "https://www.huashan1914.com//w/umaytheater/performance_21040116543451788"
    },
    {
        "event_name": "【華山親子表藝節】天馬戲創作劇團-生活中的馬戲",
        "event_image": "https://media.huashan1914.com/WebUPD/umaytheater/performance/%e7%94%9f%e6%b4%bb%e4%b8%ad%e7%9a%84%e9%a6%ac%e6%88%b2_21042310263540462.png",
        "event_date": "2021.07.24",
        "event_type": "【華山親子表藝節】工作坊\n表演藝術",
        "event_link": "https://www.huashan1914.com//w/umaytheater/performance_21040117022800628"
    },
    {
        "event_name": "【華山親子表藝節】找我劇場-快樂感官工作坊（親子戲劇場）",
        "event_image": "https://media.huashan1914.com/WebUPD/umaytheater/performance/3_21042311230023430.png",
        "event_date": "2021.07.25",
        "event_type": "【華山親子表藝節】工作坊\n表演藝術",
        "event_link": "https://www.huashan1914.com//w/umaytheater/performance_21040117093362647"
    },
    {
        "event_name": "【華山親子表藝節】找我劇場-快樂感官工作坊（親子音樂場）",
        "event_image": "https://media.huashan1914.com/WebUPD/umaytheater/performance/%e5%bf%ab%e6%a8%82%e6%84%9f%e5%ae%98%e5%b7%a5%e4%bd%9c%e5%9d%8a%ef%bc%88%e8%a6%aa%e5%ad%90%e9%9f%b3%e6%a8%82%e5%a0%b4%ef%bc%89_21042310310704236.png",
        "event_date": "2021.07.25",
        "event_type": "【華山親子表藝節】工作坊\n表演藝術",
        "event_link": "https://www.huashan1914.com//w/umaytheater/performance_21040117184713404"
    },
    {
        "event_name": "【華山親子表藝節】磚木取夥故事劇場-「各位觀眾，登場的是」—— 用燈光做顏料工作坊",
        "event_image": "https://media.huashan1914.com/WebUPD/umaytheater/performance/%e3%80%8c%e5%90%84%e4%bd%8d%e8%a7%80%e7%9c%be%ef%bc%8c%e7%99%bb%e5%a0%b4%e7%9a%84%e6%98%af%e3%80%8d%e2%80%94%e2%80%94%20%e7%94%a8%e7%87%88%e5%85%89%e5%81%9a%e9%a1%8f%e6%96%99%e5%b7%a5%e4%bd%9c%e5%9d%8a_21042310340519926.png",
        "event_date": "2021.07.25",
        "event_type": "【華山親子表藝節】工作坊\n表演藝術",
        "event_link": "https://www.huashan1914.com//w/umaytheater/performance_21040117554616420"
    },
    {
        "event_name": "【華山親子表藝節】創造焦點《Free Play》",
        "event_image": "https://media.huashan1914.com/WebUPD/umaytheater/performance/1920x1080_21050716152866463.jpg",
        "event_date": "2021.07.23 - 07.25",
        "event_type": "【華山親子表藝節】演出節目\n表演藝術",
        "event_link": "https://www.huashan1914.com//w/umaytheater/performance_21032610565417248"
    },
    {
        "event_name": "【華山親子表藝節】天馬戲創作劇團-紅旗舉起來，舞旗等你來",
        "event_image": "https://media.huashan1914.com/WebUPD/umaytheater/performance/%e7%b4%85%e6%97%97%e8%88%89%e8%b5%b7%e4%be%86%ef%bc%8c%e8%88%9e%e6%97%97%e7%ad%89%e4%bd%a0%e4%be%86_21042310374351518.png",
        "event_date": "2021.07.31",
        "event_type": "【華山親子表藝節】工作坊\n表演藝術",
        "event_link": "https://www.huashan1914.com//w/umaytheater/performance_21040118032819824"
    },
    {
        "event_name": "【華山親子表藝節】夾腳拖劇團《國王與國王》",
        "event_image": "https://media.huashan1914.com/WebUPD/umaytheater/performance/1920%20x%201080_21032615120215605.jpg",
        "event_date": "2021.07.30 - 08.01",
        "event_type": "【華山親子表藝節】演出節目\n表演藝術",
        "event_link": "https://www.huashan1914.com//w/umaytheater/performance_21032615120217260"
    },
    {
        "event_name": "【華山親子表藝節】何日君再來劇團-親子肢體互動工作坊",
        "event_image": "https://media.huashan1914.com/WebUPD/umaytheater/performance/0801%e4%bd%95%e6%97%a5%e5%90%9b%e5%86%8d%e4%be%86-%e8%a6%aa%e5%ad%90%e8%82%a2%e9%ab%94%e5%b7%a5%e4%bd%9c%e5%9d%8a(%e5%a3%93%e7%b8%ae)_21052011012499815.jpg",
        "event_date": "2021.08.01",
        "event_type": "【華山親子表藝節】工作坊\n表演藝術",
        "event_link": "https://www.huashan1914.com//w/umaytheater/performance_21040118361037512"
    },
    {
        "event_name": "華山親子表藝節×慢慢說工作坊「星球生物」——奇幻蝴蝶旋轉畫",
        "event_image": "https://media.huashan1914.com/WebUPD/umaytheater/performance/%e5%96%ae%e5%bc%b5300dppi_%e5%a5%87%e5%b9%bb%e8%9d%b4%e8%9d%b6%e6%97%8b%e8%bd%89%e7%95%ab_21050415532039473.jpg",
        "event_date": "2021.08.06",
        "event_type": "【華山親子表藝節】工作坊\n表演藝術",
        "event_link": "https://www.huashan1914.com//w/umaytheater/performance_21050415513597078"
    },
    {
        "event_name": "華山親子表藝節×慢慢說工作坊「星球火山」——火山爆發刮畫",
        "event_image": "https://media.huashan1914.com/WebUPD/umaytheater/performance/%e5%96%ae%e5%bc%b5300dppi_%e7%81%ab%e5%b1%b1%e7%88%86%e7%99%bc%e5%88%ae%e7%95%ab.jpg",
        "event_date": "2021.08.07",
        "event_type": "【華山親子表藝節】工作坊\n表演藝術",
        "event_link": "https://www.huashan1914.com//w/umaytheater/performance_21050415540144216"
    },
    {
        "event_name": "【華山親子表藝節】找我劇場-快樂感官工作坊（大人戲劇場）",
        "event_image": "https://media.huashan1914.com/WebUPD/umaytheater/performance/1.png",
        "event_date": "2021.08.07",
        "event_type": "【華山親子表藝節】工作坊\n表演藝術",
        "event_link": "https://www.huashan1914.com//w/umaytheater/performance_21040118183042622"
    },
    {
        "event_name": "【華山親子表藝節】找我劇場-快樂感官工作坊（親子繪畫場）",
        "event_image": "https://media.huashan1914.com/WebUPD/umaytheater/performance/%e5%bf%ab%e6%a8%82%e6%84%9f%e5%ae%98%e5%b7%a5%e4%bd%9c%e5%9d%8a%ef%bc%88%e8%a6%aa%e5%ad%90%e7%b9%aa%e7%95%ab%e5%a0%b4%ef%bc%89_21042310472155217.png",
        "event_date": "2021.08.07",
        "event_type": "【華山親子表藝節】工作坊\n表演藝術",
        "event_link": "https://www.huashan1914.com//w/umaytheater/performance_21040118243031504"
    },
    {
        "event_name": "華山親子表藝節×慢慢說工作坊「星球之聲」——聲音徽章",
        "event_image": "https://media.huashan1914.com/WebUPD/umaytheater/performance/%e5%96%ae%e5%bc%b5300dppi_%e8%81%b2%e9%9f%b3%e5%be%bd%e7%ab%a0_21050415572968822.jpg",
        "event_date": "2021.08.08",
        "event_type": "【華山親子表藝節】工作坊\n表演藝術",
        "event_link": "https://www.huashan1914.com//w/umaytheater/performance_21050415561000882"
    },
    {
        "event_name": "【華山親子表藝節】天馬戲創作劇團 馬戲音樂劇II《誰偷了我的，超能力！》",
        "event_image": "https://media.huashan1914.com/WebUPD/umaytheater/performance/1920%20x%201080_21032615371448985.jpg",
        "event_date": "2021.08.06 - 08.08",
        "event_type": "【華山親子表藝節】演出節目\n表演藝術",
        "event_link": "https://www.huashan1914.com//w/umaytheater/performance_21032615371450404"
    },
    {
        "event_name": "【華山親子表藝節】何日君再來劇團-繪本創作工作坊——如果如果，我是主角",
        "event_image": "https://media.huashan1914.com/WebUPD/umaytheater/performance/%e7%b9%aa%e6%9c%ac%e5%89%b5%e4%bd%9c%e5%b7%a5%e4%bd%9c%e5%9d%8a1(%e5%a3%93%e7%b8%ae)_21052011040287832.jpg",
        "event_date": "2021.08.14",
        "event_type": "【華山親子表藝節】工作坊\n表演藝術",
        "event_link": "https://www.huashan1914.com//w/umaytheater/performance_21040118295930152"
    },
    {
        "event_name": "【華山親子表藝節】磚木取夥故事劇場 《時空修復師》",
        "event_image": "https://media.huashan1914.com/WebUPD/umaytheater/performance/1920%20x%201080_21032616012656684.jpg",
        "event_date": "2021.08.13 - 08.15",
        "event_type": "【華山親子表藝節】演出節目\n表演藝術",
        "event_link": "https://www.huashan1914.com//w/umaytheater/performance_21032616012658286"
    },
    {
        "event_name": "【華山親子表藝節】何日君再來劇團-繪本創作工作坊——爸爸媽媽，我跟你們說一個故事",
        "event_image": "https://media.huashan1914.com/WebUPD/umaytheater/performance/%e7%b9%aa%e6%9c%ac%e5%89%b5%e4%bd%9c%e5%b7%a5%e4%bd%9c%e5%9d%8a2(%e5%a3%93%e7%b8%ae)_21052011061249758.jpg",
        "event_date": "2021.08.15",
        "event_type": "【華山親子表藝節】工作坊\n表演藝術",
        "event_link": "https://www.huashan1914.com//w/umaytheater/performance_21040118111103331"
    },
    {
        "event_name": "【華山親子表藝節】找我劇場 音樂繪畫劇場《展覽會之畫》",
        "event_image": "https://media.huashan1914.com/WebUPD/umaytheater/performance/1920x1080_21040810064619522.jpg",
        "event_date": "2021.08.20 - 08.22",
        "event_type": "【華山親子表藝節】演出節目\n表演藝術",
        "event_link": "https://www.huashan1914.com//w/umaytheater/performance_21040113475071834"
    },
    {
        "event_name": "【華山親子表藝節】何日君再來劇團 《艾力克斯夢遊仙境》",
        "event_image": "https://media.huashan1914.com/WebUPD/umaytheater/performance/1920x1080_21041311305609036.jpg",
        "event_date": "2021.08.27 - 08.29",
        "event_type": "【華山親子表藝節】演出節目\n表演藝術",
        "event_link": "https://www.huashan1914.com//w/umaytheater/performance_21032616350098681"
    },
    {
        "event_name": "《雙擊》許子微x許子蕎 ⋅ 打擊樂聯合音樂會",
        "event_image": "https://media.huashan1914.com/WebUPD/umaytheater/performance/IMG_3149_1920x1080_21050411232383923.jpg",
        "event_date": "2021.09.20",
        "event_type": "表演\n表演藝術",
        "event_link": "https://www.huashan1914.com//w/umaytheater/performance_21050411232385963"
    }
]